scuttlebuddy/LeagueReader.py
scuttlebuddy/Managers.py
scuttlebuddy/Models.py
scuttlebuddy/Offsets.py
scuttlebuddy/Stats.py
scuttlebuddy/Types.py
scuttlebuddy/__init__.py
scuttlebuddy-0.0.9.dist-info/LICENSE
scuttlebuddy-0.0.9.dist-info/METADATA
scuttlebuddy-0.0.9.dist-info/WHEEL
scuttlebuddy-0.0.9.dist-info/top_level.txt
scuttlebuddy-0.0.9.dist-info/RECORD
