Metadata-Version: 2.1
Name: scuttlebuddy
Version: 0.0.9
Summary: External Scripting Framework for developers who play League of Legends.
Home-page: https://discord.gg/huywRMDEmE
Author: Business
Author-email: 
License: MIT License
Project-URL: Discord, https://discord.gg/huywRMDEmE
Classifier: Development Status :: 3 - Alpha
Classifier: Programming Language :: Python :: 3.10
Classifier: Programming Language :: Python :: 3.11
Requires-Python: >=3.10,<3.12
License-File: LICENSE
Requires-Dist: requests
Requires-Dist: numpy
Requires-Dist: pywin32
Requires-Dist: orjson
